bluemist/__init__.py
bluemist/environment.py
bluemist/logging.config
bluemist/main.py
bluemist/main_predict.py
bluemist/artifacts/api/predict.py
bluemist/artifacts/api/__pycache__/predict.cpython-39.pyc
bluemist/classification/__init__.py
bluemist/datasets/auto-mpg/Index
bluemist/datasets/auto-mpg/auto-mpg.csv
bluemist/datasets/auto-mpg/auto-mpg.data
bluemist/datasets/auto-mpg/auto-mpg.data-original
bluemist/datasets/auto-mpg/auto-mpg.names
bluemist/datasource/__init__.py
bluemist/datasource/aws.py
bluemist/datasource/azure.py
bluemist/datasource/database.py
bluemist/datasource/file.py
bluemist/datasource/gcp.py
bluemist/eda/__init__.py
bluemist/eda/analyze_data.py
bluemist/llm/__init__.py
bluemist/llm/api_wrapper.py
bluemist/llm/task_models.py
bluemist/llm/test1.py
bluemist/llm/wrapper.py
bluemist/pipeline/__init__.py
bluemist/pipeline/bluemist_pipeline.py
bluemist/preprocessing/__init__.py
bluemist/preprocessing/categorical_transformer.py
bluemist/preprocessing/numeric_transformer.py
bluemist/preprocessing/preprocessor.py
bluemist/regression/__init__.py
bluemist/regression/constant.py
bluemist/regression/regressor.py
bluemist/regression/tuning/__init__.py
bluemist/regression/tuning/cuml.py
bluemist/regression/tuning/sklearn.py
bluemist/tests/__init__.py
bluemist/utils/__init__.py
bluemist/utils/constants.py
bluemist/utils/generate_api.py
bluemist/utils/metrics.py
bluemist/utils/scaler.py
bluemist-0.1.3.dist-info/LICENSE
bluemist-0.1.3.dist-info/METADATA
bluemist-0.1.3.dist-info/WHEEL
bluemist-0.1.3.dist-info/top_level.txt
bluemist-0.1.3.dist-info/RECORD
