Metadata-Version: 2.1
Name: bluemist
Version: 0.1.3
Summary: Bluemist AI is a low code machine learning library written in Python to develop, evaluate and deploy automated ML pipleines.
Home-page: https://github.com/mist-projects/bluemist-ai
Author: Shashank Agrawal
Author-email: dew@bluemist-ai.one
License: MIT
Requires-Python: >=3.9
License-File: LICENSE
Requires-Dist: fastapi (==0.97.0)
Requires-Dist: ipython (==8.12.0)
Requires-Dist: ipywidgets (==8.0.4)
Requires-Dist: Jinja2 (==3.1.2)
Requires-Dist: joblib (==1.1.1)
Requires-Dist: mlflow (==2.3.2)
Requires-Dist: nest-asyncio (==1.5.6)
Requires-Dist: numpy (==1.23.5)
Requires-Dist: pandas (==1.5.2)
Requires-Dist: py-cpuinfo (~=8.0.0)
Requires-Dist: pydantic (==1.10.2)
Requires-Dist: pyngrok (==6.0.0)
Requires-Dist: scikit-learn (==1.2.2)
Requires-Dist: scikit-learn-intelex (==2023.1.1)
Requires-Dist: setuptools (==67.8.0)
Requires-Dist: termcolor (==2.3.0)
Requires-Dist: tqdm (==4.66.1)
Requires-Dist: uvicorn (==0.16.0)
Requires-Dist: ydata-profiling (==4.3.1)
Provides-Extra: complete
Requires-Dist: boto3 (==1.26.155) ; extra == 'complete'
Requires-Dist: cx-Oracle (==8.3.0) ; extra == 'complete'
Requires-Dist: dtale (==2.16.0) ; extra == 'complete'
Requires-Dist: SQLAlchemy (==1.4.39) ; extra == 'complete'
Requires-Dist: sweetviz (==2.1.4) ; extra == 'complete'
Requires-Dist: huggingface-hub (~=0.16.4) ; extra == 'complete'
Requires-Dist: pytesseract (~=0.3.10) ; extra == 'complete'
Requires-Dist: torch (==2.1.0) ; extra == 'complete'
Requires-Dist: transformers (~=4.28.1) ; extra == 'complete'
